Hellbot/__init__.py
HellBot-0.0.4.dist-info/LICENSE
HellBot-0.0.4.dist-info/METADATA
HellBot-0.0.4.dist-info/WHEEL
HellBot-0.0.4.dist-info/top_level.txt
HellBot-0.0.4.dist-info/RECORD
