Metadata-Version: 2.1
Name: HellBot
Version: 0.0.4
Summary: HellBot IS BEST
Home-page: https://github.com/hellboy-op
Author: Hellboy and ILMA THE CODER
Author-email: Hellboyorg@gmail.com
License: UNKNOWN
Platform: UNKNOWN
Classifier: Programming Language :: Python :: 3
Classifier: License :: OSI Approved :: MIT License
Classifier: Operating System :: OS Independent
